<?xml version="1.0"?>
<mods:mods xmlns:mods="http://www.loc.gov/mods/v3">
  <mods:identifier type="local">rbml.css.0311</mods:identifier>
  <mods:name authority="naf" type="corporate">
    <mods:namePart>New York Association for Improving the Condition of the Poor</mods:namePart>
  </mods:name>
  <mods:name authority="naf" type="corporate">
    <mods:namePart>Community Service Society of New York</mods:namePart>
    <mods:role>
      <mods:roleTerm authority="marcrelator" type="text">Collector</mods:roleTerm>
    </mods:role>
  </mods:name>
  <mods:titleInfo>
    <mods:title>Women's Work Room Album -- Women's Work Shop</mods:title>
  </mods:titleInfo>
  <mods:originInfo>
    <mods:dateCreated>circa 1917</mods:dateCreated>
    <mods:dateCreated encoding="w3cdtf" keyDate="yes" point="start" qualifier="approximate">1917</mods:dateCreated>
    <mods:dateCreated encoding="w3cdtf" point="end">1918</mods:dateCreated>
  </mods:originInfo>
  <mods:physicalDescription>
    <mods:form authority="aat">photographs</mods:form>
    <mods:digitalOrigin>reformatted digital</mods:digitalOrigin>
    <mods:reformattingQuality>preservation</mods:reformattingQuality>
  </mods:physicalDescription>
  <mods:typeOfResource>still image</mods:typeOfResource>
  <mods:abstract>Annotation on back:&#xA0;From: Women's Work Room Album</mods:abstract>
  <mods:abstract>Description:&#xA0;From: Women's Work Rooms Album #4029 Unknown Photographer In AICP 75th "Annual Report 1918" (1917-1918), p. 26. Caption: WOMEN'S WORK SHOP. The large majority of the workers are elderly whomen who by reason of age and feebleness (which is often accentuated by other physical handicaps) find all other doors of work closed to them. Others are mothers, usually widows, whose home cares are such that they cannot work the regular hours required in ordinary industries but who find a few hours spent each day at the Shops opportunity for partial self-support. The work is educational in that stress is placed on the various kinds of sewing necessary in home life.</mods:abstract>
  <mods:note>Item no.&#xA0;0311</mods:note>
  <mods:note>Photograph no.&#xA0;4029</mods:note>
  <mods:note>Photographer unknown. Photograph may have been taken at 408 West 20th Street.</mods:note>
  <mods:relatedItem type="isReferencedBy">
    <mods:note>New York Association for Improving the Condition of the Poor, Annual Report 75 (New York: 1918): 26</mods:note>
  </mods:relatedItem>
  <mods:subject>
    <mods:name authority="naf">
      <mods:namePart>Women's Work Rooms (New York, N.Y.)</mods:namePart>
    </mods:name>
  </mods:subject>
  <mods:subject authority="lcsh">
    <mods:geographic>New York (N.Y.)</mods:geographic>
  </mods:subject>
  <mods:subject>
    <mods:hierarchicalGeographic>
      <mods:country>United States</mods:country>
      <mods:state>New York (State)</mods:state>
      <mods:city>New York (N.Y.)</mods:city>
      <mods:county>Manhattan</mods:county>
    </mods:hierarchicalGeographic>
  </mods:subject>
  <mods:subject authority="lcsh">
    <mods:topic>Workshops</mods:topic>
  </mods:subject>
  <mods:subject authority="lcsh">
    <mods:topic>Women--Employment</mods:topic>
  </mods:subject>
  <mods:subject authority="lcsh">
    <mods:topic>Women</mods:topic>
  </mods:subject>
  <mods:subject authority="lcsh">
    <mods:topic>Sewing</mods:topic>
  </mods:subject>
  <mods:subject authority="lcsh">
    <mods:topic>Older women</mods:topic>
  </mods:subject>
  <mods:subject authority="lcsh">
    <mods:topic>Older people--Employment</mods:topic>
  </mods:subject>
  <mods:subject authority="lcsh">
    <mods:topic>Older people</mods:topic>
  </mods:subject>
  <mods:subject authority="lcsh">
    <mods:topic>Flags</mods:topic>
  </mods:subject>
  <mods:relatedItem displayLabel="Collection" type="host">
    <mods:titleInfo>
      <mods:title>Community Service Society Records</mods:title>
    </mods:titleInfo>
  </mods:relatedItem>
  <mods:relatedItem displayLabel="Project" type="host">
    <mods:titleInfo>
      <mods:title>Community Service Society Photographs</mods:title>
    </mods:titleInfo>
    <mods:location>
      <mods:url>http://css.cul.columbia.edu</mods:url>
    </mods:location>
  </mods:relatedItem>
  <mods:location>
    <mods:physicalLocation authority="marcorg" type="code">NNC-RB</mods:physicalLocation>
    <mods:physicalLocation>Rare Book and Manuscript Library, Columbia
                    University</mods:physicalLocation>
    <mods:shelfLocator>Box no.&#xA0;298</mods:shelfLocator>
    <mods:shelfLocator>Folder no.&#xA0;36</mods:shelfLocator>
    <mods:url access="object in context" usage="primary display">http://css.cul.columbia.edu/catalog/rbml_css_0311</mods:url>
  </mods:location>
  <mods:recordInfo>
    <mods:recordContentSource authority="marcorg">NNC</mods:recordContentSource>
    <mods:languageOfCataloging>
      <mods:languageTerm authority="iso639-2b" type="code">eng</mods:languageTerm>
    </mods:languageOfCataloging>
    <mods:recordOrigin>Human created, edited in general conformance to the DLF
                    Implementation Guidelines for Shareable MODS Records, Version
                    1.1.</mods:recordOrigin>
  </mods:recordInfo>
<mods:identifier type="fedora_pid">ldpd:136742</mods:identifier></mods:mods>
