<?xml version="1.0"?>
<mods:mods xmlns:mods="http://www.loc.gov/mods/v3">
  <mods:identifier type="local">rbml.css.0122</mods:identifier>
  <mods:name authority="naf">
    <namePart>Myers, Hiram</namePart>
  </mods:name>
  <mods:name authority="naf" type="corporate">
    <mods:namePart>Community Service Society of New York</mods:namePart>
    <mods:role>
      <mods:roleTerm authority="marcrelator" type="text">Collector</mods:roleTerm>
    </mods:role>
  </mods:name>
  <mods:titleInfo>
    <mods:title>Crawford Work Shops</mods:title>
  </mods:titleInfo>
  <mods:originInfo>
    <mods:dateCreated>circa 1919</mods:dateCreated>
    <mods:dateCreated encoding="w3cdtf" keyDate="yes" qualifier="approximate">1919</mods:dateCreated>
  </mods:originInfo>Date based on publication information on CSS description sheet.<mods:physicalDescription>
    <mods:form authority="aat">photographs</mods:form>
    <mods:digitalOrigin>reformatted digital</mods:digitalOrigin>
    <mods:reformattingQuality>preservation</mods:reformattingQuality>
  </mods:physicalDescription>
  <mods:typeOfResource>still image</mods:typeOfResource>
  <mods:abstract>Annotation on back:&#xA0;From: Women's Work Rooms Album</mods:abstract>
  <mods:abstract>Description:&#xA0;Box 299 Folder 15A #5110 Stamped Hiram Myers From: Women's Work Rooms Album In "A.I.C.P. 1920"; 77th Annual Report (1919-1920), page 14 top. Caption: THE CRAWFORD WORK SHOPS. It is work and interest in life which keeps men and women - old in years - free from discouragement and bitterness, and the Crawford work shops are making a distinct contribution to society by bringing hope and cheer to scores of those who have fallen out of the race. The shops do this for men and women who often are quite alone in the world - and with whom few employers of labor care to bother. Living in small hall bedrooms in various parts of the city, mostly on the great East side, these crippled and otherwise handicapped old people find in the Crawford Shops, not only a living, but a life. In "After Three Score Years and Ten," by William H. Matthews, Director Family Department AICP. Undated. In AICP Publications, 1916-1923, #22. Probably published in 1922 or 1923. Picture facing page 27. Caption: Just where would they be - how might they have fared Had nobody bothered, had nobody cared?</mods:abstract>
  <mods:note>Item no.&#xA0;0122</mods:note>
  <mods:note>Photo may have been taken at 505 East 16th Street.</mods:note>
  <mods:relatedItem type="isReferencedBy">
    <mods:note>New York Association for Improving the Condition of the Poor, Annual Report 77 (New York: 1919-1920): 14.</mods:note>
  </mods:relatedItem>
  <mods:subject>
    <mods:name authority="naf">
      <mods:namePart>Women's Work Interiors (New York, N.Y.)</mods:namePart>
    </mods:name>
  </mods:subject>
  <mods:subject>
    <mods:name authority="naf">
      <mods:namePart>Crawford Work Shops (New York, N.Y.)</mods:namePart>
    </mods:name>
  </mods:subject>
  <mods:subject authority="lcsh">
    <mods:geographic>New York (N.Y.)</mods:geographic>
  </mods:subject>
  <mods:subject>
    <mods:hierarchicalGeographic>
      <mods:country>United States</mods:country>
      <mods:state>New York (State)</mods:state>
      <mods:city>New York (N.Y.)</mods:city>
      <mods:county>Manhattan</mods:county>
    </mods:hierarchicalGeographic>
  </mods:subject>
  <mods:subject authority="lcsh">
    <mods:topic>Workshops</mods:topic>
  </mods:subject>
  <mods:subject authority="lcsh">
    <mods:topic>Women--Employment</mods:topic>
  </mods:subject>
  <mods:subject authority="lcsh">
    <mods:topic>Women</mods:topic>
  </mods:subject>
  <mods:subject authority="lcsh">
    <mods:topic>Sewing</mods:topic>
  </mods:subject>
  <mods:subject authority="lcsh">
    <mods:topic>People with disabilities</mods:topic>
  </mods:subject>
  <mods:subject authority="lcsh">
    <mods:topic>Older women</mods:topic>
  </mods:subject>
  <mods:subject authority="lcsh">
    <mods:topic>Older people--Employment</mods:topic>
  </mods:subject>
  <mods:relatedItem displayLabel="Collection" type="host">
    <mods:titleInfo>
      <mods:title>Community Service Society Records</mods:title>
    </mods:titleInfo>
  </mods:relatedItem>
  <mods:relatedItem displayLabel="Project" type="host">
    <mods:titleInfo>
      <mods:title>Community Service Society Photographs</mods:title>
    </mods:titleInfo>
    <mods:location>
      <mods:url>http://css.cul.columbia.edu</mods:url>
    </mods:location>
  </mods:relatedItem>
  <mods:location>
    <mods:physicalLocation authority="marcorg" type="code">NNC-RB</mods:physicalLocation>
    <mods:physicalLocation>Rare Book and Manuscript Library, Columbia
                    University</mods:physicalLocation>
    <mods:shelfLocator>Box no.&#xA0;13</mods:shelfLocator>
    <mods:shelfLocator>Folder no.&#xA0;39</mods:shelfLocator>
    <mods:url access="object in context" usage="primary display">http://css.cul.columbia.edu/catalog/rbml_css_0122</mods:url>
  </mods:location>
  <mods:recordInfo>
    <mods:recordContentSource authority="marcorg">NNC</mods:recordContentSource>
    <mods:languageOfCataloging>
      <mods:languageTerm authority="iso639-2b" type="code">eng</mods:languageTerm>
    </mods:languageOfCataloging>
    <mods:recordOrigin>Human created, edited in general conformance to the DLF
                    Implementation Guidelines for Shareable MODS Records, Version
                    1.1.</mods:recordOrigin>
  </mods:recordInfo>
<mods:identifier type="fedora_pid">ldpd:136178</mods:identifier></mods:mods>
