<?xml version="1.0"?>
<mods:mods xmlns:mods="http://www.loc.gov/mods/v3">
  <mods:identifier type="local">rbml.css.0108</mods:identifier>
  <mods:name authority="naf" type="corporate">
    <mods:namePart>New York Association for Improving the Condition of the Poor</mods:namePart>
  </mods:name>
  <mods:name authority="naf">
    <namePart>Myers, Hiram</namePart>
  </mods:name>
  <mods:name authority="naf" type="corporate">
    <mods:namePart>Community Service Society of New York</mods:namePart>
    <mods:role>
      <mods:roleTerm authority="marcrelator" type="text">Collector</mods:roleTerm>
    </mods:role>
  </mods:name>
  <mods:titleInfo>
    <mods:title>Mulberry Health Center Album -- Dietician Weighing Child</mods:title>
  </mods:titleInfo>
  <mods:originInfo>
    <mods:dateCreated>circa 1918</mods:dateCreated>
    <mods:dateCreated encoding="w3cdtf" keyDate="yes" qualifier="approximate">1918</mods:dateCreated>
  </mods:originInfo>
  <mods:physicalDescription>
    <mods:form authority="aat">photographs</mods:form>
    <mods:digitalOrigin>reformatted digital</mods:digitalOrigin>
    <mods:reformattingQuality>preservation</mods:reformattingQuality>
  </mods:physicalDescription>
  <mods:typeOfResource>still image</mods:typeOfResource>
  <mods:abstract>Annotation on back:&#xA0;From: Mulberry Health Center Album</mods:abstract>
  <mods:abstract>Description:&#xA0;Box 298 Folder 12 # 4136 Stamped Hiram Myers From: Mulberry Health Center Album See: #4135 Same home In "Last Year's Work and This Year's Challenge", 76th Annual Report of AICP (1918-1919). Picture at p. 11, top right. Caption: Part of the Dietitian's Work. Beside picture: "The dietitian was so determined to know the weight of the ailing children she was treating and to interest and encourage the mother that she invented a weighing device that she could tuck under her arm, carry into the heme, and hang on the doorway." Also in: AICP publication "Developing Child Health via Community Organization," c1919, p. 16, bottom. Caption: The tiny toddlers are weighed weekly by the nutrition worker in the home with this portable scale. Bagdad on the Subway; A Periodical of Association News, No. 7, Sept. 1919, p. 14. Illustration for article entitled, "Child Health Work." Caption: Keeping Tab on the Baby's Weight.</mods:abstract>
  <mods:note>Item no.&#xA0;0108</mods:note>
  <mods:note>Photograph no.&#xA0;4136</mods:note>
  <mods:note>Same home as depicted in image no. 0200 of this digital collection.</mods:note>
  <mods:relatedItem type="isReferencedBy">
    <mods:note>New York Association for Improving the Condition of the Poor, Annual Report 76 (New York: 1918-19): 11; New York Association for Improving the Condition of the Poor, "Developing Child Health via Community Organization" (New York: 1919): 16; New York Association for Improving the Condition of the Poor, Bagdad on the Subway 7 (1919): 14.</mods:note>
  </mods:relatedItem>
  <mods:subject>
    <mods:name authority="naf">
      <mods:namePart>Mulberry Health Center (New York, N.Y.)</mods:namePart>
    </mods:name>
  </mods:subject>
  <mods:subject authority="lcsh">
    <mods:geographic>New York (N.Y.)</mods:geographic>
  </mods:subject>
  <mods:subject>
    <mods:hierarchicalGeographic>
      <mods:country>United States</mods:country>
      <mods:state>New York (State)</mods:state>
      <mods:city>New York (N.Y.)</mods:city>
      <mods:county>Manhattan</mods:county>
    </mods:hierarchicalGeographic>
  </mods:subject>
  <mods:subject authority="lcsh">
    <mods:topic>Women</mods:topic>
  </mods:subject>
  <mods:subject authority="lcsh">
    <mods:topic>Weighing instruments</mods:topic>
  </mods:subject>
  <mods:subject authority="lcsh">
    <mods:topic>Scales (Weighing instruments)</mods:topic>
  </mods:subject>
  <mods:subject authority="lcsh">
    <mods:topic>Dietitians</mods:topic>
  </mods:subject>
  <mods:subject authority="lcsh">
    <mods:topic>Children--Health and hygiene</mods:topic>
  </mods:subject>
  <mods:subject authority="lcsh">
    <mods:topic>Children</mods:topic>
  </mods:subject>
  <mods:relatedItem displayLabel="Collection" type="host">
    <mods:titleInfo>
      <mods:title>Community Service Society Records</mods:title>
    </mods:titleInfo>
  </mods:relatedItem>
  <mods:relatedItem displayLabel="Project" type="host">
    <mods:titleInfo>
      <mods:title>Community Service Society Photographs</mods:title>
    </mods:titleInfo>
    <mods:location>
      <mods:url>http://css.cul.columbia.edu</mods:url>
    </mods:location>
  </mods:relatedItem>
  <mods:location>
    <mods:physicalLocation authority="marcorg" type="code">NNC-RB</mods:physicalLocation>
    <mods:physicalLocation>Rare Book and Manuscript Library, Columbia
                    University</mods:physicalLocation>
    <mods:shelfLocator>Box no.&#xA0;13</mods:shelfLocator>
    <mods:shelfLocator>Folder no.&#xA0;25</mods:shelfLocator>
    <mods:url access="object in context" usage="primary display">http://css.cul.columbia.edu/catalog/rbml_css_0108</mods:url>
  </mods:location>
  <mods:recordInfo>
    <mods:recordContentSource authority="marcorg">NNC</mods:recordContentSource>
    <mods:languageOfCataloging>
      <mods:languageTerm authority="iso639-2b" type="code">eng</mods:languageTerm>
    </mods:languageOfCataloging>
    <mods:recordOrigin>Human created, edited in general conformance to the DLF
                    Implementation Guidelines for Shareable MODS Records, Version
                    1.1.</mods:recordOrigin>
  </mods:recordInfo>
<mods:identifier type="fedora_pid">ldpd:136136</mods:identifier></mods:mods>
