<?xml version="1.0"?>
<mods:mods xmlns:mods="http://www.loc.gov/mods/v3">
  <mods:identifier type="local">rbml.css.1275</mods:identifier>
  <mods:name authority="naf" type="corporate">
    <mods:namePart>Community Service Society of New York</mods:namePart>
    <mods:role>
      <mods:roleTerm authority="marcrelator" type="text">Collector</mods:roleTerm>
    </mods:role>
  </mods:name>
  <mods:titleInfo>
    <mods:title>Making Daily Report</mods:title>
  </mods:titleInfo>
  <mods:originInfo>
    <mods:dateCreated>circa 1907</mods:dateCreated>
    <mods:dateCreated encoding="w3cdtf" keyDate="yes" qualifier="approximate">1907</mods:dateCreated>
  </mods:originInfo>
  <mods:physicalDescription>
    <mods:form authority="aat">photographs</mods:form>
    <mods:digitalOrigin>reformatted digital</mods:digitalOrigin>
    <mods:reformattingQuality>preservation</mods:reformattingQuality>
  </mods:physicalDescription>
  <mods:typeOfResource>still image</mods:typeOfResource>
  <mods:abstract>Annotation on back:&#xA0;Book 3 22 prints minimounted Same finish Ehatt Junior Sea Breeze 64th St., East River, N.Y. City.</mods:abstract>
  <mods:abstract>Description:&#xA0;In &#x201C;64th Annual Report of The New York Association for Improving the Condition of The Poor, September 30th, 1907.&#x201D; Picture at the beginning of report (paging starts at page 8). Caption: &#x201C;Making the Daily Report. Visiting Staff &#x2013; Junior Sea Breeze.&#x201D; (See 63rd AICP Annual Report, year ending Sept. 30, 1906, p. 68ff, for story of beginning of Junior Sea Breeze, at 64th Street and East River. The &#x201C;beautiful old Colonial mansion&#x201D; was undoubtedly the Schermerhorn&#x2019;s, as they formerly owned the land, and the mansion was once summer home of Governor George Clinton. Picture of mansion opposite p. 68.) This picture, and the two on following page, were sent to the CSS Department of Public Interest July 4, 1950, by Miss Helen Fuller, Director, Ward Manor, with a note saying, &#x201C;One of our most beloved family members, Evelina M. Haughwout, died recently. She had been a worker for Junior Sea Breeze Hospital for AICP back in 1907 and among her papers I found this story about it (filed Archives History file, Seabreeze) and these pictures. I thought they might have some use in our archives some day &#x2026;&#x201D; Junior Sea Breeze was &#x201C;discontinued&#x201D; Sept. 30, 1911. See AICP 69th Annual Report, 1911-12, pp. 15-16.</mods:abstract>
  <mods:note>Item no.&#xA0;1275</mods:note>
  <mods:note>Photograph no.&#xA0;352</mods:note>
  <mods:note>Photographer unknown.</mods:note>
  <mods:relatedItem type="isReferencedBy">
    <mods:note>New York Association for Improving the Condition of the Poor, Annual Report 64 (New York: 1906-1907).</mods:note>
  </mods:relatedItem>
  <mods:subject authority="lcsh">
    <mods:geographic>New York (N.Y.)</mods:geographic>
  </mods:subject>
  <mods:subject>
    <mods:hierarchicalGeographic>
      <mods:country>United States</mods:country>
      <mods:state>New York (State)</mods:state>
      <mods:city>New York (N.Y.)</mods:city>
      <mods:county>Manhattan</mods:county>
      <mods:citySection>64th Street</mods:citySection>
    </mods:hierarchicalGeographic>
  </mods:subject>
  <mods:subject authority="lcsh">
    <mods:topic>Women</mods:topic>
  </mods:subject>
  <mods:subject authority="lcsh">
    <mods:topic>Telephone</mods:topic>
  </mods:subject>
  <mods:subject authority="lcsh">
    <mods:topic>Social workers</mods:topic>
  </mods:subject>
  <mods:subject authority="lcsh">
    <mods:topic>Office furniture</mods:topic>
  </mods:subject>
  <mods:relatedItem displayLabel="Collection" type="host">
    <mods:titleInfo>
      <mods:title>Community Service Society Records</mods:title>
    </mods:titleInfo>
  </mods:relatedItem>
  <mods:relatedItem displayLabel="Project" type="host">
    <mods:titleInfo>
      <mods:title>Community Service Society Photographs</mods:title>
    </mods:titleInfo>
    <mods:location>
      <mods:url>http://css.cul.columbia.edu</mods:url>
    </mods:location>
  </mods:relatedItem>
  <mods:location>
    <mods:physicalLocation authority="marcorg" type="code">NNC-RB</mods:physicalLocation>
    <mods:physicalLocation>Rare Book and Manuscript Library, Columbia
                    University</mods:physicalLocation>
    <mods:shelfLocator>Box no.&#xA0;296</mods:shelfLocator>
    <mods:shelfLocator>Folder no.&#xA0;51</mods:shelfLocator>
    <mods:url access="object in context" usage="primary display">http://css.cul.columbia.edu/catalog/rbml_css_1275</mods:url>
  </mods:location>
  <mods:recordInfo>
    <mods:recordContentSource authority="marcorg">NNC</mods:recordContentSource>
    <mods:languageOfCataloging>
      <mods:languageTerm authority="iso639-2b" type="code">eng</mods:languageTerm>
    </mods:languageOfCataloging>
    <mods:recordOrigin>Human created, edited in general conformance to the DLF
                    Implementation Guidelines for Shareable MODS Records, Version
                    1.1.</mods:recordOrigin>
  </mods:recordInfo>
<mods:identifier type="fedora_pid">ldpd:139625</mods:identifier></mods:mods>
