<?xml version="1.0"?>
<mods:mods xmlns:mods="http://www.loc.gov/mods/v3">
  <mods:identifier type="local">rbml.css.1261</mods:identifier>
  <mods:name authority="naf" type="corporate">
    <mods:namePart>Community Service Society of New York</mods:namePart>
    <mods:role>
      <mods:roleTerm authority="marcrelator" type="text">Collector</mods:roleTerm>
    </mods:role>
  </mods:name>
  <mods:titleInfo>
    <mods:title>Exit to Roof of New Shaft</mods:title>
  </mods:titleInfo>
  <mods:originInfo>
    <mods:dateCreated>circa 1900</mods:dateCreated>
    <mods:dateCreated encoding="w3cdtf" keyDate="yes" qualifier="approximate">1900</mods:dateCreated>
  </mods:originInfo>
  <mods:physicalDescription>
    <mods:form authority="aat">photographs</mods:form>
    <mods:digitalOrigin>reformatted digital</mods:digitalOrigin>
    <mods:reformattingQuality>preservation</mods:reformattingQuality>
  </mods:physicalDescription>
  <mods:typeOfResource>still image</mods:typeOfResource>
  <mods:abstract>Annotation on back:&#xA0;Division St. Mnht Exit to roof of new shaft in relation to bulk head and dumbwaiter shaft.</mods:abstract>
  <mods:abstract>Description:&#xA0;Written on back: Division Street, Manhattan. Exit to roof of new shaft in relation to bulk head and dumbwaiter shaft. This photo may also have been part of the Tenement House Exhibition of 1900. See article by Lawrence Veiller in Charities Review (Vol. X), March 1900, no. 1, pp. 19-27.</mods:abstract>
  <mods:note>Item no.&#xA0;1261</mods:note>
  <mods:note>Photograph no.&#xA0;540</mods:note>
  <mods:subject authority="lcsh">
    <mods:geographic>New York (N.Y.)</mods:geographic>
  </mods:subject>
  <mods:subject authority="lcsh">
    <mods:geographic>Lower East Side (New York, N.Y.)</mods:geographic>
  </mods:subject>
  <mods:subject>
    <mods:hierarchicalGeographic>
      <mods:country>United States</mods:country>
      <mods:state>New York (State)</mods:state>
      <mods:city>New York (N.Y.)</mods:city>
      <mods:county>Manhattan</mods:county>
      <mods:citySection>Division Street</mods:citySection>
    </mods:hierarchicalGeographic>
  </mods:subject>
  <mods:subject authority="lcsh">
    <mods:topic>Tenement houses</mods:topic>
  </mods:subject>
  <mods:subject authority="lcsh">
    <mods:topic>Roofs</mods:topic>
  </mods:subject>
  <mods:relatedItem displayLabel="Collection" type="host">
    <mods:titleInfo>
      <mods:title>Community Service Society Records</mods:title>
    </mods:titleInfo>
  </mods:relatedItem>
  <mods:relatedItem displayLabel="Project" type="host">
    <mods:titleInfo>
      <mods:title>Community Service Society Photographs</mods:title>
    </mods:titleInfo>
    <mods:location>
      <mods:url>http://css.cul.columbia.edu</mods:url>
    </mods:location>
  </mods:relatedItem>
  <mods:location>
    <mods:physicalLocation authority="marcorg" type="code">NNC-RB</mods:physicalLocation>
    <mods:physicalLocation>Rare Book and Manuscript Library, Columbia
                    University</mods:physicalLocation>
    <mods:shelfLocator>Box no.&#xA0;296</mods:shelfLocator>
    <mods:shelfLocator>Folder no.&#xA0;37</mods:shelfLocator>
    <mods:url access="object in context" usage="primary display">http://css.cul.columbia.edu/catalog/rbml_css_1261</mods:url>
  </mods:location>
  <mods:recordInfo>
    <mods:recordContentSource authority="marcorg">NNC</mods:recordContentSource>
    <mods:languageOfCataloging>
      <mods:languageTerm authority="iso639-2b" type="code">eng</mods:languageTerm>
    </mods:languageOfCataloging>
    <mods:recordOrigin>Human created, edited in general conformance to the DLF
                    Implementation Guidelines for Shareable MODS Records, Version
                    1.1.</mods:recordOrigin>
  </mods:recordInfo>
<mods:identifier type="fedora_pid">ldpd:139583</mods:identifier></mods:mods>
