<?xml version="1.0"?>
<mods:mods xmlns:mods="http://www.loc.gov/mods/v3">
  <mods:identifier type="local">rbml.css.0549</mods:identifier>
  <mods:name authority="naf" type="corporate">
    <mods:namePart>New York Association for Improving the Condition of the Poor</mods:namePart>
  </mods:name>
  <mods:name authority="naf" type="corporate">
    <mods:namePart>Community Service Society of New York</mods:namePart>
    <mods:role>
      <mods:roleTerm authority="marcrelator" type="text">Collector</mods:roleTerm>
    </mods:role>
  </mods:name>
  <mods:titleInfo>
    <mods:title>Columbus Hill Health Center Album -- Two Women with Babies</mods:title>
  </mods:titleInfo>
  <mods:originInfo>
    <mods:dateCreated>circa 1919</mods:dateCreated>
    <mods:dateCreated encoding="w3cdtf" keyDate="yes" qualifier="approximate">1919</mods:dateCreated>
  </mods:originInfo>
  <mods:physicalDescription>
    <mods:form authority="aat">photographs</mods:form>
    <mods:digitalOrigin>reformatted digital</mods:digitalOrigin>
    <mods:reformattingQuality>preservation</mods:reformattingQuality>
  </mods:physicalDescription>
  <mods:typeOfResource>still image</mods:typeOfResource>
  <mods:abstract>Annotation on back:&#xA0;From: Columbus Hill Health Center Album.</mods:abstract>
  <mods:abstract>Description:&#xA0;From: Columbus Hill Health Center Album. AICP Pamphlet "Developing Child Health Care via Community Organization," c1919, page 8. Caption: Two undernourished babies being cared for under our supervision.</mods:abstract>
  <mods:note>Item no.&#xA0;0549</mods:note>
  <mods:note>Photograph no.&#xA0;4367</mods:note>
  <mods:note>Photographer unknown.</mods:note>
  <mods:relatedItem type="isReferencedBy">
    <mods:note>New York Association for Improving the Condition of the Poor, "Developing Child Health Care via Community Organization" (New York: 1919): 8.</mods:note>
  </mods:relatedItem>
  <mods:subject>
    <mods:name authority="naf">
      <mods:namePart>Columbus Hill Health Center (New York, N.Y.)</mods:namePart>
    </mods:name>
  </mods:subject>
  <mods:subject authority="lcsh">
    <mods:geographic>New York (N.Y.)</mods:geographic>
  </mods:subject>
  <mods:subject>
    <mods:hierarchicalGeographic>
      <mods:country>United States</mods:country>
      <mods:state>New York (State)</mods:state>
      <mods:city>New York (N.Y.)</mods:city>
      <mods:county>Manhattan</mods:county>
    </mods:hierarchicalGeographic>
  </mods:subject>
  <mods:subject authority="lcsh">
    <mods:topic>Women</mods:topic>
  </mods:subject>
  <mods:subject authority="lcsh">
    <mods:topic>Children--Nutrition</mods:topic>
  </mods:subject>
  <mods:subject authority="lcsh">
    <mods:topic>Children--Health and hygiene</mods:topic>
  </mods:subject>
  <mods:subject authority="lcsh">
    <mods:topic>Children</mods:topic>
  </mods:subject>
  <mods:subject authority="lcsh">
    <mods:topic>Babies</mods:topic>
  </mods:subject>
  <mods:subject authority="lcsh">
    <mods:topic>African Americans</mods:topic>
  </mods:subject>
  <mods:relatedItem displayLabel="Collection" type="host">
    <mods:titleInfo>
      <mods:title>Community Service Society Records</mods:title>
    </mods:titleInfo>
  </mods:relatedItem>
  <mods:relatedItem displayLabel="Project" type="host">
    <mods:titleInfo>
      <mods:title>Community Service Society Photographs</mods:title>
    </mods:titleInfo>
    <mods:location>
      <mods:url>http://css.cul.columbia.edu</mods:url>
    </mods:location>
  </mods:relatedItem>
  <mods:location>
    <mods:physicalLocation authority="marcorg" type="code">NNC-RB</mods:physicalLocation>
    <mods:physicalLocation>Rare Book and Manuscript Library, Columbia
                    University</mods:physicalLocation>
    <mods:shelfLocator>Box no.&#xA0;299</mods:shelfLocator>
    <mods:shelfLocator>Folder no.&#xA0;66</mods:shelfLocator>
    <mods:url access="object in context" usage="primary display">http://css.cul.columbia.edu/catalog/rbml_css_0549</mods:url>
  </mods:location>
  <mods:recordInfo>
    <mods:recordContentSource authority="marcorg">NNC</mods:recordContentSource>
    <mods:languageOfCataloging> 
     <mods:languageTerm authority="iso639-2b" type="code">eng</mods:languageTerm>
    </mods:languageOfCataloging>
    <mods:recordOrigin>Human created, edited in general conformance to the DLF
                    Implementation Guidelines for Shareable MODS Records, Version
                    1.1.</mods:recordOrigin>
  </mods:recordInfo>
<mods:identifier type="fedora_pid">ldpd:137456</mods:identifier></mods:mods>
